[
  {
    "id": 1,
    "name": "Розы",
    "description": "Королева цветов, символ любви и красоты."
  },
  {
    "id": 2,
    "name": "Пионы",
    "description": "Нежные и пышные цветы, символ богатства и процветания."
  },
  {
    "id": 3,
    "name": "Хризантемы",
    "description": "Символ долголетия и оптимизма."
  },
  {
    "id": 4,
    "name": "Лилии",
    "description": "Символ чистоты и благородства."
  },
  {
    "id": 5,
    "name": "Герберы",
    "description": "Символ радости и хорошего настроения."
  },
  {
    "id": 6,
    "name": "Тюльпаны",
    "description": "Символ радости и хорошего настроения."
  },
  {
    "id": 7,
    "name": "Сборные букеты"
  },
  {
    "id": 8,
    "name": "Откытки"
  },
  {
    "id": 9,
    "name": "Игрушки"
  }
]
